task2/f1_fsm.sv
module f1_fsm   #(
    parameter WIDTH = 8
)(
    input logic clk, // clock
    input logic rst, // synchronous reset
    input logic en,  // input trigger signal
    output logic [WIDTH-1:0] data_out // output signal
);

    // Defining states
    typedef enum  {s0, s1, s2, s3, s4, s5, s6, s7, s8} states;
    states current_state, next_state;

    //state registers
    always_ff @( posedge clk, posedge rst )
        if (rst)        current_state <= s0;
        else if (en)    current_state <= next_state;

    // next state logic
    always_comb begin
        case(current_state)
        s0:  next_state = s1;
        s1:  next_state = s2;
        s2:  next_state = s3;
        s3:  next_state = s4;
        s4:  next_state = s5;
        s5:  next_state = s6;
        s6:  next_state = s7;
        s7:  next_state = s8;
        s8:  next_state = s0;
        default: next_state = s0;
        endcase
    end

    // output logic
    always_comb begin
        case(current_state)
        s0:         data_out = 8'b0;
        s1:         data_out = 8'b1;
        s2:         data_out = 8'b11;
        s3:         data_out = 8'b111;
        s4:         data_out = 8'b1111;
        s5:         data_out = 8'b11111;
        s6:         data_out = 8'b111111;
        s7:         data_out = 8'b1111111;
        s8:         data_out = 8'b11111111;
        default:    data_out = 8'b0;
        endcase
    end

endmodule

task3/task4/clktick.sv
module clktick #(
	parameter WIDTH = 5
)(
  // interface signals
  input  logic             clk,      // clock 
  input  logic             rst,      // reset
  input  logic             en,       // enable signal
  input  logic [WIDTH-1:0] N,     	 // clock divided by N+1
  output logic  		       tick      // tick output
);

logic [WIDTH-1:0] count;

always_ff @ (posedge clk, posedge rst)
    if (rst) begin
        tick <= 1'b0;
        count <= N;  
        end
    else if (en) begin
	    if (count == 0) begin
		    tick <= 1'b1;
		    count <= N;
	        end
	    else begin
		    tick <= 1'b0;
		    count <= count - 1'b1;
	        end
        end
endmodule

task3/delay_light.sv
module delay_light # (
    parameter   WIDTH = 8,
                N_WIDTH = 16
)(
    // interface signals
    input   logic                   clk,
    input   logic                   rst,
    input   logic                   en,
    input   logic   [N_WIDTH-1:0]   N, 
    output  logic   [WIDTH-1:0]     data_out
);

    logic pulse; // interconnection wire

clktick ticker(
    .clk(clk),
    .rst(rst),
    .en(en),
    .N(N),
    .tick(pulse)
);

f1_fsm lights(
    .clk(clk),
    .rst(rst),
    .en(pulse),
    .data_out(data_out)
);

endmodule

task3/delay_light.vcd
$version Generated by VerilatedVcd $end
$date Sun Nov  5 23:18:50 2023 $end
$timescale 1ps $end

 $scope module TOP $end
  $var wire 16 * N [15:0] $end
  $var wire  1 ' clk $end
  $var wire  8 + data_out [7:0] $end
  $var wire  1 ) en $end
  $var wire  1 ( rst $end
  $scope module delay_light $end
   $var wire 16 * N [15:0] $end
   $var wire 32 - N_WIDTH [31:0] $end
   $var wire 32 , WIDTH [31:0] $end
   $var wire  1 ' clk $end
   $var wire  8 + data_out [7:0] $end
   $var wire  1 ) en $end
   $var wire  1 # pulse $end
   $var wire  1 ( rst $end
   $scope module lights $end
    $var wire 32 , WIDTH [31:0] $end
    $var wire  1 ' clk $end
    $var wire 32 $ current_state [31:0] $end
    $var wire  8 + data_out [7:0] $end
    $var wire  1 # en $end
    $var wire 32 % next_state [31:0] $end
    $var wire  1 ( rst $end
   $upscope $end
   $scope module ticker $end
    $var wire 16 * N [15:0] $end
    $var wire 32 - WIDTH [31:0] $end
    $var wire  1 ' clk $end
    $var wire 16 & count [15:0] $end
    $var wire  1 ) en $end
    $var wire  1 ( rst $end
    $var wire  1 # tick $end
   $upscope $end
  $upscope $end
 $upscope $end
$enddefinitions $end


#0
0#
b00000000000000000000000000000000 $
b00000000000000000000000000000001 %
b0000000000000000 &
1'
0(
1)
b0000000000100100 *
b00000000 +
b00000000000000000000000000001000 ,
b00000000000000000000000000010000 -
#1
0'
#2
1#
b0000000000100100 &
1'
1(
b0000000000110011 *
#3
0#
b0000000000110011 &
0'
#4
1'
#5
0'
#6
1'
0(
#7
0'
#8
b0000000000110010 &
1'
#9
0'
#10
b0000000000110001 &
1'
#11
0'
#12
b0000000000110000 &
1'
#13
0'
#14
b0000000000101111 &
1'
#15
0'
#16
b0000000000101110 &
1'
#17
0'
#18
b0000000000101101 &
1'
#19
0'
#20
b0000000000101100 &
1'
#21
0'
#22
b0000000000101011 &
1'
#23
0'
#24
b0000000000101010 &
1'
#25
0'
#26
b0000000000101001 &
1'
#27
0'
#28
b0000000000101000 &
1'
#29
0'
#30
b0000000000100111 &
1'
#31
0'
#32
b0000000000100110 &
1'
#33
0'
#34
b0000000000100101 &
1'
#35
0'
#36
b0000000000100100 &
1'
#37
0'
#38
b0000000000100011 &
1'
#39
0'
#40
b0000000000100010 &
1'
#41
0'
#42
b0000000000100001 &
1'
#43
0'
#44
b0000000000100000 &
1'
#45
0'
#46
b0000000000011111 &
1'
#47
0'
#48
b0000000000011110 &
1'
#49
0'
#50
b0000000000011101 &
1'
#51
0'
#52
b0000000000011100 &
1'
#53
0'
#54
b0000000000011011 &
1'
#55
0'
#56
b0000000000011010 &
1'
#57
0'
#58
b0000000000011001 &
1'
#59
0'
#60
b0000000000011000 &
1'
#61
0'
#62
b0000000000010111 &
1'
#63
0'
#64
b0000000000010110 &
1'
#65
0'
#66
b0000000000010101 &
1'
#67
0'
#68
b0000000000010100 &
1'
#69
0'
#70
b0000000000010011 &
1'
#71
0'
#72
b0000000000010010 &
1'
#73
0'
#74
b0000000000010001 &
1'
#75
0'
#76
b0000000000010000 &
1'
#77
0'
#78
b0000000000001111 &
1'
#79
0'
#80
b0000000000001110 &
1'
#81
0'
#82
b0000000000001101 &
1'
#83
0'
#84
b0000000000001100 &
1'
#85
0'
#86
b0000000000001011 &
1'
#87
0'
#88
b0000000000001010 &
1'
#89
0'
#90
b0000000000001001 &
1'
#91
0'
#92
b0000000000001000 &
1'
#93
0'
#94
b0000000000000111 &
1'
#95
0'
#96
b0000000000000110 &
1'
#97
0'
#98
b0000000000000101 &
1'
#99
0'
#100
b0000000000000100 &
1'
#101
0'
#102
b0000000000000011 &
1'
#103
0'
#104
b0000000000000010 &
1'
#105
0'
#106
b0000000000000001 &
1'
#107
0'
#108
b0000000000000000 &
1'
#109
0'
#110
1#
b0000000000110011 &
1'
#111
0'
#112
0#
b00000000000000000000000000000001 $
b00000000000000000000000000000010 %
b0000000000110010 &
1'
b00000001 +
#113
0'
#114
b0000000000110001 &
1'
#115
0'
#116
b0000000000110000 &
1'
#117
0'
#118
b0000000000101111 &
1'
#119
0'
#120
b0000000000101110 &
1'
#121
0'
#122
b0000000000101101 &
1'
#123
0'
#124
b0000000000101100 &
1'
#125
0'
#126
b0000000000101011 &
1'
#127
0'
#128
b0000000000101010 &
1'
#129
0'
#130
b0000000000101001 &
1'
#131
0'
#132
b0000000000101000 &
1'
#133
0'
#134
b0000000000100111 &
1'
#135
0'
#136
b0000000000100110 &
1'
#137
0'
#138
b0000000000100101 &
1'
#139
0'
#140
b0000000000100100 &
1'
#141
0'
#142
b0000000000100011 &
1'
#143
0'
#144
b0000000000100010 &
1'
#145
0'
#146
b0000000000100001 &
1'
#147
0'
#148
b0000000000100000 &
1'
#149
0'
#150
b0000000000011111 &
1'
#151
0'
#152
b0000000000011110 &
1'
#153
0'
#154
b0000000000011101 &
1'
#155
0'
#156
b0000000000011100 &
1'
#157
0'
#158
b0000000000011011 &
1'
#159
0'
#160
b0000000000011010 &
1'
#161
0'
#162
b0000000000011001 &
1'
#163
0'
#164
b0000000000011000 &
1'
#165
0'
#166
b0000000000010111 &
1'
#167
0'
#168
b0000000000010110 &
1'
#169
0'
#170
b0000000000010101 &
1'
#171
0'
#172
b0000000000010100 &
1'
#173
0'
#174
b0000000000010011 &
1'
#175
0'
#176
b0000000000010010 &
1'
#177
0'
#178
b0000000000010001 &
1'
#179
0'
#180
b0000000000010000 &
1'
#181
0'
#182
b0000000000001111 &
1'
#183
0'
#184
b0000000000001110 &
1'
#185
0'
#186
b0000000000001101 &
1'
#187
0'
#188
b0000000000001100 &
1'
#189
0'
#190
b0000000000001011 &
1'
#191
0'
#192
b0000000000001010 &
1'
#193
0'
#194
b0000000000001001 &
1'
#195
0'
#196
b0000000000001000 &
1'
#197
0'
#198
b0000000000000111 &
1'
#199
0'
#200
b0000000000000110 &
1'
#201
0'
#202
b0000000000000101 &
1'
#203
0'
#204
b0000000000000100 &
1'
#205
0'
#206
b0000000000000011 &
1'
#207
0'
#208
b0000000000000010 &
1'
#209
0'
#210
b0000000000000001 &
1'
#211
0'
#212
b0000000000000000 &
1'
#213
0'
#214
1#
b0000000000110011 &
1'
#215
0'
#216
0#
b00000000000000000000000000000010 $
b00000000000000000000000000000011 %
b0000000000110010 &
1'
b00000011 +
#217
0'
#218
b0000000000110001 &
1'
#219
0'
#220
b0000000000110000 &
1'
#221
0'
#222
b0000000000101111 &
1'
#223
0'
#224
b0000000000101110 &
1'
#225
0'
#226
b0000000000101101 &
1'
#227
0'
#228
b0000000000101100 &
1'
#229
0'
#230
b0000000000101011 &
1'
#231
0'
#232
b0000000000101010 &
1'
#233
0'
#234
b0000000000101001 &
1'
#235
0'
#236
b0000000000101000 &
1'
#237
0'
#238
b0000000000100111 &
1'
#239
0'
#240
b0000000000100110 &
1'
#241
0'
#242
b0000000000100101 &
1'
#243
0'
#244
b0000000000100100 &
1'
#245
0'
#246
b0000000000100011 &
1'
#247
0'
#248
b0000000000100010 &
1'
#249
0'
#250
b0000000000100001 &
1'
#251
0'
#252
b0000000000100000 &
1'
#253
0'
#254
b0000000000011111 &
1'
#255
0'
#256
b0000000000011110 &
1'
#257
0'
#258
b0000000000011101 &
1'
#259
0'
#260
b0000000000011100 &
1'
#261
0'
#262
b0000000000011011 &
1'
#263
0'
#264
b0000000000011010 &
1'
#265
0'
#266
b0000000000011001 &
1'
#267
0'
#268
b0000000000011000 &
1'
#269
0'
#270
b0000000000010111 &
1'
#271
0'
#272
b0000000000010110 &
1'
#273
0'
#274
b0000000000010101 &
1'
#275
0'
#276
b0000000000010100 &
1'
#277
0'
#278
b0000000000010011 &
1'
#279
0'
#280
b0000000000010010 &
1'
#281
0'
#282
b0000000000010001 &
1'
#283
0'
#284
b0000000000010000 &
1'
#285
0'
#286
b0000000000001111 &
1'
#287
0'
#288
b0000000000001110 &
1'
#289
0'
#290
b0000000000001101 &
1'
#291
0'
#292
b0000000000001100 &
1'
#293
0'
#294
b0000000000001011 &
1'
#295
0'
#296
b0000000000001010 &
1'
#297
0'
#298
b0000000000001001 &
1'
#299
0'
#300
b0000000000001000 &
1'
#301
0'
#302
b0000000000000111 &
1'
#303
0'
#304
b0000000000000110 &
1'
#305
0'
#306
b0000000000000101 &
1'
#307
0'
#308
b0000000000000100 &
1'
#309
0'
#310
b0000000000000011 &
1'
#311
0'
#312
b0000000000000010 &
1'
#313
0'
#314
b0000000000000001 &
1'
#315
0'
#316
b0000000000000000 &
1'
#317
0'
#318
1#
b0000000000110011 &
1'
#319
0'
#320
0#
b00000000000000000000000000000011 $
b00000000000000000000000000000100 %
b0000000000110010 &
1'
b00000111 +
#321
0'
#322
b0000000000110001 &
1'
#323
0'
#324
b0000000000110000 &
1'
#325
0'
#326
b0000000000101111 &
1'
#327
0'
#328
b0000000000101110 &
1'
#329
0'
#330
b0000000000101101 &
1'
#331
0'
#332
b0000000000101100 &
1'
#333
0'
#334
b0000000000101011 &
1'
#335
0'
#336
b0000000000101010 &
1'
#337
0'
#338
b0000000000101001 &
1'
#339
0'
#340
b0000000000101000 &
1'
#341
0'
#342
b0000000000100111 &
1'
#343
0'
#344
b0000000000100110 &
1'
#345
0'
#346
b0000000000100101 &
1'
#347
0'
#348
b0000000000100100 &
1'
#349
0'
#350
b0000000000100011 &
1'
#351
0'
#352
b0000000000100010 &
1'
#353
0'
#354
b0000000000100001 &
1'
#355
0'
#356
b0000000000100000 &
1'
#357
0'
#358
b0000000000011111 &
1'
#359
0'
#360
b0000000000011110 &
1'
#361
0'
#362
b0000000000011101 &
1'
#363
0'
#364
b0000000000011100 &
1'
#365
0'
#366
b0000000000011011 &
1'
#367
0'
#368
b0000000000011010 &
1'
#369
0'
#370
b0000000000011001 &
1'
#371
0'
#372
b0000000000011000 &
1'
#373
0'
#374
b0000000000010111 &
1'
#375
0'
#376
b0000000000010110 &
1'
#377
0'
#378
b0000000000010101 &
1'
#379
0'
#380
b0000000000010100 &
1'
#381
0'
#382
b0000000000010011 &
1'
#383
0'
#384
b0000000000010010 &
1'
#385
0'
#386
b0000000000010001 &
1'
#387
0'
#388
b0000000000010000 &
1'
#389
0'
#390
b0000000000001111 &
1'
#391
0'
#392
b0000000000001110 &
1'
#393
0'
#394
b0000000000001101 &
1'
#395
0'
#396
b0000000000001100 &
1'
#397
0'
#398
b0000000000001011 &
1'
#399
0'
#400
b0000000000001010 &
1'
#401
0'
#402
b0000000000001001 &
1'
#403
0'
#404
b0000000000001000 &
1'
#405
0'
#406
b0000000000000111 &
1'
#407
0'
#408
b0000000000000110 &
1'
#409
0'
#410
b0000000000000101 &
1'
#411
0'
#412
b0000000000000100 &
1'
#413
0'
#414
b0000000000000011 &
1'
#415
0'
#416
b0000000000000010 &
1'
#417
0'
#418
b0000000000000001 &
1'
#419
0'
#420
b0000000000000000 &
1'
#421
0'
#422
1#
b0000000000110011 &
1'
#423
0'
#424
0#
b00000000000000000000000000000100 $
b00000000000000000000000000000101 %
b0000000000110010 &
1'
b00001111 +
#425
0'
#426
b0000000000110001 &
1'
#427
0'
#428
b0000000000110000 &
1'
#429
0'
#430
b0000000000101111 &
1'
#431
0'
#432
b0000000000101110 &
1'
#433
0'
#434
b0000000000101101 &
1'
#435
0'
#436
b0000000000101100 &
1'
#437
0'
#438
b0000000000101011 &
1'
#439
0'
#440
b0000000000101010 &
1'
#441
0'
#442
b0000000000101001 &
1'
#443
0'
#444
b0000000000101000 &
1'
#445
0'
#446
b0000000000100111 &
1'
#447
0'
#448
b0000000000100110 &
1'
#449
0'
#450
b0000000000100101 &
1'
#451
0'
#452
b0000000000100100 &
1'
#453
0'
#454
b0000000000100011 &
1'
#455
0'
#456
b0000000000100010 &
1'
#457
0'
#458
b0000000000100001 &
1'
#459
0'
#460
b0000000000100000 &
1'
#461
0'
#462
b0000000000011111 &
1'
#463
0'
#464
b0000000000011110 &
1'
#465
0'
#466
b0000000000011101 &
1'
#467
0'
#468
b0000000000011100 &
1'
#469
0'
#470
b0000000000011011 &
1'
#471
0'
#472
b0000000000011010 &
1'
#473
0'
#474
b0000000000011001 &
1'
#475
0'
#476
b0000000000011000 &
1'
#477
0'
#478
b0000000000010111 &
1'
#479
0'
#480
b0000000000010110 &
1'
#481
0'
#482
b0000000000010101 &
1'
#483
0'
#484
b0000000000010100 &
1'
#485
0'
#486
b0000000000010011 &
1'
#487
0'
#488
b0000000000010010 &
1'
#489
0'
#490
b0000000000010001 &
1'
#491
0'
#492
b0000000000010000 &
1'
#493
0'
#494
b0000000000001111 &
1'
#495
0'
#496
b0000000000001110 &
1'
#497
0'
#498
b0000000000001101 &
1'
#499
0'
#500
b0000000000001100 &
1'
#501
0'
#502
b0000000000001011 &
1'
#503
0'
#504
b0000000000001010 &
1'
#505
0'
#506
b0000000000001001 &
1'
#507
0'
#508
b0000000000001000 &
1'
#509
0'
#510
b0000000000000111 &
1'
#511
0'
#512
b0000000000000110 &
1'
#513
0'
#514
b0000000000000101 &
1'
#515
0'
#516
b0000000000000100 &
1'
#517
0'
#518
b0000000000000011 &
1'
#519
0'
#520
b0000000000000010 &
1'
#521
0'
#522
b0000000000000001 &
1'
#523
0'
#524
b0000000000000000 &
1'
#525
0'
#526
1#
b0000000000110011 &
1'
#527
0'
#528
0#
b00000000000000000000000000000101 $
b00000000000000000000000000000110 %
b0000000000110010 &
1'
b00011111 +
#529
0'
#530
b0000000000110001 &
1'
#531
0'
#532
b0000000000110000 &
1'
#533
0'
#534
b0000000000101111 &
1'
#535
0'
#536
b0000000000101110 &
1'
#537
0'
#538
b0000000000101101 &
1'
#539
0'
#540
b0000000000101100 &
1'
#541
0'
#542
b0000000000101011 &
1'
#543
0'
#544
b0000000000101010 &
1'
#545
0'
#546
b0000000000101001 &
1'
#547
0'
#548
b0000000000101000 &
1'
#549
0'
#550
b0000000000100111 &
1'
#551
0'
#552
b0000000000100110 &
1'
#553
0'
#554
b0000000000100101 &
1'
#555
0'
#556
b0000000000100100 &
1'
#557
0'
#558
b0000000000100011 &
1'
#559
0'
#560
b0000000000100010 &
1'
#561
0'
#562
b0000000000100001 &
1'
#563
0'
#564
b0000000000100000 &
1'
#565
0'
#566
b0000000000011111 &
1'
#567
0'
#568
b0000000000011110 &
1'
#569
0'
#570
b0000000000011101 &
1'
#571
0'
#572
b0000000000011100 &
1'
#573
0'
#574
b0000000000011011 &
1'
#575
0'
#576
b0000000000011010 &
1'
#577
0'
#578
b0000000000011001 &
1'
#579
0'
#580
b0000000000011000 &
1'
#581
0'
#582
b0000000000010111 &
1'
#583
0'
#584
b0000000000010110 &
1'
#585
0'
#586
b0000000000010101 &
1'
#587
0'
#588
b0000000000010100 &
1'
#589
0'
#590
b0000000000010011 &
1'
#591
0'
#592
b0000000000010010 &
1'
#593
0'
#594
b0000000000010001 &
1'
#595
0'
#596
b0000000000010000 &
1'
#597
0'
#598
b0000000000001111 &
1'
#599
0'
#600
b0000000000001110 &
1'
#601
0'
#602
b0000000000001101 &
1'
#603
0'
#604
b0000000000001100 &
1'
#605
0'
#606
b0000000000001011 &
1'
#607
0'
#608
b0000000000001010 &
1'
#609
0'
#610
b0000000000001001 &
1'
#611
0'
#612
b0000000000001000 &
1'
#613
0'
#614
b0000000000000111 &
1'
#615
0'
#616
b0000000000000110 &
1'
#617
0'
#618
b0000000000000101 &
1'
#619
0'
#620
b0000000000000100 &
1'
#621
0'
#622
b0000000000000011 &
1'
#623
0'
#624
b0000000000000010 &
1'
#625
0'
#626
b0000000000000001 &
1'
#627
0'
#628
b0000000000000000 &
1'
#629
0'
#630
1#
b0000000000110011 &
1'
#631
0'
#632
0#
b00000000000000000000000000000110 $
b00000000000000000000000000000111 %
b0000000000110010 &
1'
b00111111 +
#633
0'
#634
b0000000000110001 &
1'
#635
0'
#636
b0000000000110000 &
1'
#637
0'
#638
b0000000000101111 &
1'
#639
0'
#640
b0000000000101110 &
1'
#641
0'
#642
b0000000000101101 &
1'
#643
0'
#644
b0000000000101100 &
1'
#645
0'
#646
b0000000000101011 &
1'
#647
0'
#648
b0000000000101010 &
1'
#649
0'
#650
b0000000000101001 &
1'
#651
0'
#652
b0000000000101000 &
1'
#653
0'
#654
b0000000000100111 &
1'
#655
0'
#656
b0000000000100110 &
1'
#657
0'
#658
b0000000000100101 &
1'
#659
0'
#660
b0000000000100100 &
1'
#661
0'
#662
b0000000000100011 &
1'
#663
0'
#664
b0000000000100010 &
1'
#665
0'
#666
b0000000000100001 &
1'
#667
0'
#668
b0000000000100000 &
1'
#669
0'
#670
b0000000000011111 &
1'
#671
0'
#672
b0000000000011110 &
1'
#673
0'
#674
b0000000000011101 &
1'
#675
0'
#676
b0000000000011100 &
1'
#677
0'
#678
b0000000000011011 &
1'
#679
0'
#680
b0000000000011010 &
1'
#681
0'
#682
b0000000000011001 &
1'
#683
0'
#684
b0000000000011000 &
1'
#685
0'
#686
b0000000000010111 &
1'
#687
0'
#688
b0000000000010110 &
1'
#689
0'
#690
b0000000000010101 &
1'
#691
0'
#692
b0000000000010100 &
1'
#693
0'
#694
b0000000000010011 &
1'
#695
0'
#696
b0000000000010010 &
1'
#697
0'
#698
b0000000000010001 &
1'
#699
0'
#700
b0000000000010000 &
1'
#701
0'
#702
b0000000000001111 &
1'
#703
0'
#704
b0000000000001110 &
1'
#705
0'
#706
b0000000000001101 &
1'
#707
0'
#708
b0000000000001100 &
1'
#709
0'
#710
b0000000000001011 &
1'
#711
0'
#712
b0000000000001010 &
1'
#713
0'
#714
b0000000000001001 &
1'
#715
0'
#716
b0000000000001000 &
1'
#717
0'
#718
b0000000000000111 &
1'
#719
0'
#720
b0000000000000110 &
1'
#721
0'
#722
b0000000000000101 &
1'
#723
0'
#724
b0000000000000100 &
1'
#725
0'
#726
b0000000000000011 &
1'
#727
0'
#728
b0000000000000010 &
1'
#729
0'
#730
b0000000000000001 &
1'
#731
0'
#732
b0000000000000000 &
1'
#733
0'
#734
1#
b0000000000110011 &
1'
#735
0'
#736
0#
b00000000000000000000000000000111 $
b00000000000000000000000000001000 %
b0000000000110010 &
1'
b01111111 +
#737
0'
#738
b0000000000110001 &
1'
#739
0'
#740
b0000000000110000 &
1'
#741
0'
#742
b0000000000101111 &
1'
#743
0'
#744
b0000000000101110 &
1'
#745
0'
#746
b0000000000101101 &
1'
#747
0'
#748
b0000000000101100 &
1'
#749
0'
#750
b0000000000101011 &
1'
#751
0'
#752
b0000000000101010 &
1'
#753
0'
#754
b0000000000101001 &
1'
#755
0'
#756
b0000000000101000 &
1'
#757
0'
#758
b0000000000100111 &
1'
#759
0'
#760
b0000000000100110 &
1'
#761
0'
#762
b0000000000100101 &
1'
#763
0'
#764
b0000000000100100 &
1'
#765
0'
#766
b0000000000100011 &
1'
#767
0'
#768
b0000000000100010 &
1'
#769
0'
#770
b0000000000100001 &
1'
#771
0'
#772
b0000000000100000 &
1'
#773
0'
#774
b0000000000011111 &
1'
#775
0'
#776
b0000000000011110 &
1'
#777
0'
#778
b0000000000011101 &
1'
#779
0'
#780
b0000000000011100 &
1'
#781
0'
#782
b0000000000011011 &
1'
#783
0'
#784
b0000000000011010 &
1'
#785
0'
#786
b0000000000011001 &
1'
#787
0'
#788
b0000000000011000 &
1'
#789
0'
#790
b0000000000010111 &
1'
#791
0'
#792
b0000000000010110 &
1'
#793
0'
#794
b0000000000010101 &
1'
#795
0'
#796
b0000000000010100 &
1'
#797
0'
#798
b0000000000010011 &
1'
#799
0'
#800
b0000000000010010 &
1'
#801
0'
#802
b0000000000010001 &
1'
#803
0'
#804
b0000000000010000 &
1'
#805
0'
#806
b0000000000001111 &
1'
#807
0'
#808
b0000000000001110 &
1'
#809
0'
#810
b0000000000001101 &
1'
#811
0'
#812
b0000000000001100 &
1'
#813
0'
#814
b0000000000001011 &
1'
#815
0'
#816
b0000000000001010 &
1'
#817
0'
#818
b0000000000001001 &
1'
#819
0'
#820
b0000000000001000 &
1'
#821
0'
#822
b0000000000000111 &
1'
#823
0'
#824
b0000000000000110 &
1'
#825
0'
#826
b0000000000000101 &
1'
#827
0'
#828
b0000000000000100 &
1'
#829
0'
#830
b0000000000000011 &
1'
#831
0'
#832
b0000000000000010 &
1'
#833
0'
#834
b0000000000000001 &
1'
#835
0'
#836
b0000000000000000 &
1'
#837
0'
#838
1#
b0000000000110011 &
1'
#839
0'
#840
0#
b00000000000000000000000000001000 $
b00000000000000000000000000000000 %
b0000000000110010 &
1'
b11111111 +
#841
0'
#842
b0000000000110001 &
1'
#843
0'
#844
b0000000000110000 &
1'
#845
0'
#846
b0000000000101111 &
1'
#847
0'
#848
b0000000000101110 &
1'
#849
0'
#850
b0000000000101101 &
1'
#851
0'
#852
b0000000000101100 &
1'
#853
0'
#854
b0000000000101011 &
1'
#855
0'
#856
b0000000000101010 &
1'
#857
0'
#858
b0000000000101001 &
1'
#859
0'
#860
b0000000000101000 &
1'
#861
0'
#862
b0000000000100111 &
1'
#863
0'
#864
b0000000000100110 &
1'
#865
0'
#866
b0000000000100101 &
1'
#867
0'
#868
b0000000000100100 &
1'
#869
0'
#870
b0000000000100011 &
1'
#871
0'
#872
b0000000000100010 &
1'
#873
0'
#874
b0000000000100001 &
1'
#875
0'
#876
b0000000000100000 &
1'
#877
0'
#878
b0000000000011111 &
1'
#879
0'
#880
b0000000000011110 &
1'
#881
0'
#882
b0000000000011101 &
1'
#883
0'
#884
b0000000000011100 &
1'
#885
0'
#886
b0000000000011011 &
1'
#887
0'
#888
b0000000000011010 &
1'
#889
0'
#890
b0000000000011001 &
1'
#891
0'
#892
b0000000000011000 &
1'
#893
0'
#894
b0000000000010111 &
1'
#895
0'
#896
b0000000000010110 &
1'
#897
0'
#898
b0000000000010101 &
1'
#899
0'
#900
b0000000000010100 &
1'
#901
0'
#902
b0000000000010011 &
1'
#903
0'
#904
b0000000000010010 &
1'
#905
0'
#906
b0000000000010001 &
1'
#907
0'
#908
b0000000000010000 &
1'
#909
0'
#910
b0000000000001111 &
1'
#911
0'
#912
b0000000000001110 &
1'
#913
0'
#914
b0000000000001101 &
1'
#915
0'
#916
b0000000000001100 &
1'
#917
0'
#918
b0000000000001011 &
1'
#919
0'
#920
b0000000000001010 &
1'
#921
0'
#922
b0000000000001001 &
1'
#923
0'
#924
b0000000000001000 &
1'
#925
0'
#926
b0000000000000111 &
1'
#927
0'
#928
b0000000000000110 &
1'
#929
0'
#930
b0000000000000101 &
1'
#931
0'
#932
b0000000000000100 &
1'
#933
0'
#934
b0000000000000011 &
1'
#935
0'
#936
b0000000000000010 &
1'
#937
0'
#938
b0000000000000001 &
1'
#939
0'
#940
b0000000000000000 &
1'
#941
0'
#942
1#
b0000000000110011 &
1'
#943
0'
#944
0#
b00000000000000000000000000000000 $
b00000000000000000000000000000001 %
b0000000000110010 &
1'
b00000000 +
#945
0'
#946
b0000000000110001 &
1'
#947
0'
#948
b0000000000110000 &
1'
#949
0'
#950
b0000000000101111 &
1'
#951
0'
#952
b0000000000101110 &
1'
#953
0'
#954
b0000000000101101 &
1'
#955
0'
#956
b0000000000101100 &
1'
#957
0'
#958
b0000000000101011 &
1'
#959
0'
#960
b0000000000101010 &
1'
#961
0'
#962
b0000000000101001 &
1'
#963
0'
#964
b0000000000101000 &
1'
#965
0'
#966
b0000000000100111 &
1'
#967
0'
#968
b0000000000100110 &
1'
#969
0'
#970
b0000000000100101 &
1'
#971
0'
#972
b0000000000100100 &
1'
#973
0'
#974
b0000000000100011 &
1'
#975
0'
#976
b0000000000100010 &
1'
#977
0'
#978
b0000000000100001 &
1'
#979
0'
#980
b0000000000100000 &
1'
#981
0'
#982
b0000000000011111 &
1'
#983
0'
#984
b0000000000011110 &
1'
#985
0'
#986
b0000000000011101 &
1'
#987
0'
#988
b0000000000011100 &
1'
#989
0'
#990
b0000000000011011 &
1'
#991
0'
#992
b0000000000011010 &
1'
#993
0'
#994
b0000000000011001 &
1'
#995
0'
#996
b0000000000011000 &
1'
#997
0'
#998
b0000000000010111 &
1'
#999
0'
#1000
b0000000000010110 &
1'
#1001
0'
#1002
b0000000000010101 &
1'
#1003
0'
#1004
b0000000000010100 &
1'
#1005
0'
#1006
b0000000000010011 &
1'
#1007
0'
#1008
b0000000000010010 &
1'
#1009
0'
#1010
b0000000000010001 &
1'
#1011
0'
#1012
b0000000000010000 &
1'
#1013
0'
#1014
b0000000000001111 &
1'
#1015
0'
#1016
b0000000000001110 &
1'
#1017
0'
#1018
b0000000000001101 &
1'
#1019
0'
#1020
b0000000000001100 &
1'
#1021
0'
#1022
b0000000000001011 &
1'
#1023
0'
#1024
b0000000000001010 &
1'
#1025
0'
#1026
b0000000000001001 &
1'
#1027
0'
#1028
b0000000000001000 &
1'
#1029
0'
#1030
b0000000000000111 &
1'
#1031
0'
#1032
b0000000000000110 &
1'
#1033
0'
#1034
b0000000000000101 &
1'
#1035
0'
#1036
b0000000000000100 &
1'
#1037
0'
#1038
b0000000000000011 &
1'
#1039
0'
#1040
b0000000000000010 &
1'
#1041
0'
#1042
b0000000000000001 &
1'
#1043
0'
#1044
b0000000000000000 &
1'
#1045
0'
#1046
1#
b0000000000110011 &
1'
#1047
0'
#1048
0#
b00000000000000000000000000000001 $
b00000000000000000000000000000010 %
b0000000000110010 &
1'
b00000001 +
#1049
0'
#1050
b0000000000110001 &
1'
#1051
0'
#1052
b0000000000110000 &
1'
#1053
0'
#1054
b0000000000101111 &
1'
#1055
0'
#1056
b0000000000101110 &
1'
#1057
0'
#1058
b0000000000101101 &
1'
#1059
0'
#1060
b0000000000101100 &
1'
#1061
0'
#1062
b0000000000101011 &
1'
#1063
0'
#1064
b0000000000101010 &
1'
#1065
0'
#1066
b0000000000101001 &
1'
#1067
0'
#1068
b0000000000101000 &
1'
#1069
0'
#1070
b0000000000100111 &
1'
#1071
0'
#1072
b0000000000100110 &
1'
#1073
0'
#1074
b0000000000100101 &
1'
#1075
0'
#1076
b0000000000100100 &
1'
#1077
0'
#1078
b0000000000100011 &
1'
#1079
0'
#1080
b0000000000100010 &
1'
#1081
0'
#1082
b0000000000100001 &
1'
#1083
0'
#1084
b0000000000100000 &
1'
#1085
0'
#1086
b0000000000011111 &
1'
#1087
0'
#1088
b0000000000011110 &
1'
#1089
0'
#1090
b0000000000011101 &
1'
#1091
0'
#1092
b0000000000011100 &
1'
#1093
0'
#1094
b0000000000011011 &
1'
#1095
0'
#1096
b0000000000011010 &
1'
#1097
0'
#1098
b0000000000011001 &
1'
#1099
0'
#1100
b0000000000011000 &
1'
#1101
0'
#1102
b0000000000010111 &
1'
#1103
0'
#1104
b0000000000010110 &
1'
#1105
0'
#1106
b0000000000010101 &
1'
#1107
0'
#1108
b0000000000010100 &
1'
#1109
0'
#1110
b0000000000010011 &
1'
#1111
0'
#1112
b0000000000010010 &
1'
#1113
0'
#1114
b0000000000010001 &
1'
#1115
0'
#1116
b0000000000010000 &
1'
#1117
0'
#1118
b0000000000001111 &
1'
#1119
0'
#1120
b0000000000001110 &
1'
#1121
0'
#1122
b0000000000001101 &
1'
#1123
0'
#1124
b0000000000001100 &
1'
#1125
0'
#1126
b0000000000001011 &
1'
#1127
0'
#1128
b0000000000001010 &
1'
#1129
0'
#1130
b0000000000001001 &
1'
#1131
0'
#1132
b0000000000001000 &
1'
#1133
0'
#1134
b0000000000000111 &
1'
#1135
0'
#1136
b0000000000000110 &
1'
#1137
0'
#1138
b0000000000000101 &
1'
#1139
0'
#1140
b0000000000000100 &
1'
#1141
0'
#1142
b0000000000000011 &
1'
